MANIFEST.in
README
pylintrc
requirements.txt
setup.py
tox.ini
src/pemjh/__init__.py
src/pemjh.egg-info/PKG-INFO
src/pemjh.egg-info/SOURCES.txt
src/pemjh.egg-info/dependency_links.txt
src/pemjh.egg-info/top_level.txt
src/pemjh/challenge001/__init__.py
src/pemjh/challenge002/__init__.py
src/pemjh/challenge003/__init__.py
src/pemjh/challenge004/__init__.py
src/pemjh/challenge005/__init__.py
src/pemjh/challenge006/__init__.py
src/pemjh/challenge007/__init__.py
src/pemjh/challenge008/__init__.py
src/pemjh/challenge009/__init__.py
src/pemjh/challenge010/__init__.py
src/pemjh/challenge011/__init__.py
src/pemjh/challenge012/__init__.py
src/pemjh/challenge013/__init__.py
src/pemjh/challenge014/__init__.py
src/pemjh/challenge015/__init__.py
src/pemjh/challenge016/__init__.py
src/pemjh/challenge017/__init__.py
src/pemjh/challenge018/__init__.py
src/pemjh/challenge019/__init__.py
src/pemjh/challenge020/__init__.py
src/pemjh/challenge021/__init__.py
src/pemjh/challenge022/__init__.py
src/pemjh/challenge022/names.txt
src/pemjh/challenge023/__init__.py
src/pemjh/challenge024/__init__.py
src/pemjh/challenge025/__init__.py
src/pemjh/challenge026/__init__.py
src/pemjh/challenge027/__init__.py
src/pemjh/challenge028/__init__.py
src/pemjh/challenge029/__init__.py
src/pemjh/challenge030/__init__.py
src/pemjh/challenge031/__init__.py
src/pemjh/challenge032/__init__.py
src/pemjh/challenge033/__init__.py
src/pemjh/challenge034/__init__.py
src/pemjh/challenge035/__init__.py
src/pemjh/challenge036/__init__.py
src/pemjh/challenge037/__init__.py
src/pemjh/challenge038/__init__.py
src/pemjh/challenge039/__init__.py
src/pemjh/challenge040/__init__.py
src/pemjh/challenge041/__init__.py
src/pemjh/challenge042/__init__.py
src/pemjh/challenge042/words.txt
src/pemjh/challenge043/__init__.py
src/pemjh/challenge044/__init__.py
src/pemjh/challenge045/__init__.py
src/pemjh/challenge046/__init__.py
src/pemjh/challenge047/__init__.py
src/pemjh/challenge048/__init__.py
src/pemjh/challenge049/__init__.py
src/pemjh/challenge050/__init__.py
src/pemjh/challenge051/__init__.py
src/pemjh/challenge052/__init__.py
