Metadata-Version: 1.1
Name: pemjh
Version: 0.0.1
Summary: Project euler (https://projecteuler.net/) challenge code in Python.
Home-page: none.non
Author: Matthew Hussey
Author-email: matthew.hussey@googlemail.com
License: None, private use by myself only
Keywords: code challenge euler
Platform: UNKNOWN
Classifier: Development Status :: 1 - Planning
